rgevolve/wet_3/jms/__init__.py
rgevolve/wet_3/jms/_version.py
rgevolve/wet_3/jms/data.h5
rgevolve_wet_3_jms-0.1.1.dist-info/licenses/LICENSE
rgevolve_wet_3_jms-0.1.1.dist-info/METADATA
rgevolve_wet_3_jms-0.1.1.dist-info/WHEEL
rgevolve_wet_3_jms-0.1.1.dist-info/top_level.txt
rgevolve_wet_3_jms-0.1.1.dist-info/RECORD
